vulkan_engine/__init__.py
vulkan_engine/config.py
vulkan_engine/config_variables.py
vulkan_engine/db.py
vulkan_engine/exceptions.py
vulkan_engine/schemas.py
vulkan_engine/utils.py
vulkan_engine/backends/__init__.py
vulkan_engine/backends/data_client.py
vulkan_engine/backends/execution.py
vulkan_engine/backends/service_client.py
vulkan_engine/backends/dagster/__init__.py
vulkan_engine/backends/dagster/backend.py
vulkan_engine/backends/dagster/client.py
vulkan_engine/backends/dagster/data_client.py
vulkan_engine/backends/dagster/service_client.py
vulkan_engine/backends/dagster/trigger_run.py
vulkan_engine/backends/factory/__init__.py
vulkan_engine/backends/factory/backend.py
vulkan_engine/backends/factory/data_client.py
vulkan_engine/backends/factory/service_client.py
vulkan_engine/backends/hatchet/__init__.py
vulkan_engine/backends/hatchet/backend.py
vulkan_engine/backends/hatchet/data_client.py
vulkan_engine/backends/hatchet/service_client.py
vulkan_engine/data/__init__.py
vulkan_engine/data/broker.py
vulkan_engine/loaders/__init__.py
vulkan_engine/loaders/base.py
vulkan_engine/loaders/component.py
vulkan_engine/loaders/data_source.py
vulkan_engine/loaders/policy.py
vulkan_engine/loaders/policy_version.py
vulkan_engine/loaders/run.py
vulkan_engine/logging/__init__.py
vulkan_engine/logging/config.py
vulkan_engine/logging/logger.py
vulkan_engine/services/__init__.py
vulkan_engine/services/allocation.py
vulkan_engine/services/auth_handler.py
vulkan_engine/services/base.py
vulkan_engine/services/component.py
vulkan_engine/services/data_source.py
vulkan_engine/services/data_source_analytics.py
vulkan_engine/services/data_source_test.py
vulkan_engine/services/policy.py
vulkan_engine/services/policy_analytics.py
vulkan_engine/services/policy_version.py
vulkan_engine/services/request_preparation.py
vulkan_engine/services/run_orchestration.py
vulkan_engine/services/run_query.py
vulkan_engine/services/workflow.py
vulkan_engine/services/credential/credential.py
vulkanlabs_vulkan_engine-0.1.0.dev20251119095008.dist-info/METADATA
vulkanlabs_vulkan_engine-0.1.0.dev20251119095008.dist-info/WHEEL
vulkanlabs_vulkan_engine-0.1.0.dev20251119095008.dist-info/RECORD
