Metadata-Version: 2.4
Name: vulkanlabs-vulkan-engine
Version: 0.1.0.dev20251119095008
Summary: Vulkan core engine
Requires-Python: >=3.10
Requires-Dist: alembic>=1.13.0
Requires-Dist: dagster-graphql>=1.8.2
Requires-Dist: httpx>=0.24.0
Requires-Dist: pandas>=2.2.3
Requires-Dist: pydantic>=2.8.2
Requires-Dist: redis>=5.0.0
Requires-Dist: requests>=2.32.3
Requires-Dist: sqlalchemy>=2.0.32
Requires-Dist: structlog>=24.1.0
Requires-Dist: vulkanlabs-vulkan[dagster,hatchet]
